pymindcore/__init__.py
pymindcore/core.py
pymindcore/errors.py
pymindcore/plugins.py
pymindcore-0.2.11.dist-info/LICENSE
pymindcore-0.2.11.dist-info/METADATA
pymindcore-0.2.11.dist-info/WHEEL
pymindcore-0.2.11.dist-info/top_level.txt
pymindcore-0.2.11.dist-info/RECORD
